{
  "フシギダネ": "https://yakkun.com/za/zukan/n1",
  "フシギソウ": "https://yakkun.com/za/zukan/n2",
  "フシギバナ": "https://yakkun.com/za/zukan/n3",
  "メガフシギバナ": "https://yakkun.com/za/zukan/n3m",
  "ヒトカゲ": "https://yakkun.com/za/zukan/n4",
  "リザード": "https://yakkun.com/za/zukan/n5",
  "リザードン": "https://yakkun.com/za/zukan/n6",
  "メガリザードンＸ": "https://yakkun.com/za/zukan/n6x",
  "メガリザードンＹ": "https://yakkun.com/za/zukan/n6y",
  "ゼニガメ": "https://yakkun.com/za/zukan/n7",
  "カメール": "https://yakkun.com/za/zukan/n8",
  "カメックス": "https://yakkun.com/za/zukan/n9",
  "メガカメックス": "https://yakkun.com/za/zukan/n9m",
  "キャタピー": "https://yakkun.com/swsh/zukan/n10",
  "トランセル": "https://yakkun.com/swsh/zukan/n11",
  "バタフリー": "https://yakkun.com/swsh/zukan/n12",
  "ビードル": "https://yakkun.com/za/zukan/n13",
  "コクーン": "https://yakkun.com/za/zukan/n14",
  "スピアー": "https://yakkun.com/za/zukan/n15",
  "メガスピアー": "https://yakkun.com/za/zukan/n15m",
  "ポッポ": "https://yakkun.com/za/zukan/n16",
  "ピジョン": "https://yakkun.com/za/zukan/n17",
  "ピジョット": "https://yakkun.com/za/zukan/n18",
  "メガピジョット": "https://yakkun.com/za/zukan/n18m",
  "コラッタ": "https://yakkun.com/bdsp/zukan/n19",
  "コラッタ(アローラのすがた)": "https://yakkun.com/sm/zukan/n19a",
  "ラッタ": "https://yakkun.com/bdsp/zukan/n20",
  "ラッタ(アローラのすがた)": "https://yakkun.com/sm/zukan/n20a",
  "オニスズメ": "https://yakkun.com/bdsp/zukan/n21",
  "オニドリル": "https://yakkun.com/bdsp/zukan/n22",
  "アーボ": "https://yakkun.com/za/zukan/n23",
  "アーボック": "https://yakkun.com/za/zukan/n24",
  "ピカチュウ": "https://yakkun.com/za/zukan/n25",
  "ライチュウ": "https://yakkun.com/za/zukan/n26",
  "ライチュウ(アローラのすがた)": "https://yakkun.com/za/zukan/n26a",
  "サンド": "https://yakkun.com/sv/zukan/n27",
  "サンド(アローラのすがた)": "https://yakkun.com/sv/zukan/n27a",
  "サンドパン": "https://yakkun.com/sv/zukan/n28",
  "サンドパン(アローラのすがた)": "https://yakkun.com/sv/zukan/n28a",
  "ニドラン♀": "https://yakkun.com/swsh/zukan/n29",
  "ニドリーナ": "https://yakkun.com/swsh/zukan/n30",
  "ニドクイン": "https://yakkun.com/swsh/zukan/n31",
  "ニドラン♂": "https://yakkun.com/swsh/zukan/n32",
  "ニドリーノ": "https://yakkun.com/swsh/zukan/n33",
  "ニドキング": "https://yakkun.com/swsh/zukan/n34",
  "ピッピ": "https://yakkun.com/za/zukan/n35",
  "ピクシー": "https://yakkun.com/za/zukan/n36",
  "メガピクシー": "https://yakkun.com/za/zukan/n36m",
  "ロコン": "https://yakkun.com/sv/zukan/n37",
  "ロコン(アローラのすがた)": "https://yakkun.com/sv/zukan/n37a",
  "キュウコン": "https://yakkun.com/sv/zukan/n38",
  "キュウコン(アローラのすがた)": "https://yakkun.com/sv/zukan/n38a",
  "プリン": "https://yakkun.com/za/zukan/n39",
  "プクリン": "https://yakkun.com/za/zukan/n40",
  "ズバット": "https://yakkun.com/za/zukan/n41",
  "ゴルバット": "https://yakkun.com/za/zukan/n42",
  "ナゾノクサ": "https://yakkun.com/sv/zukan/n43",
  "クサイハナ": "https://yakkun.com/sv/zukan/n44",
  "ラフレシア": "https://yakkun.com/sv/zukan/n45",
  "パラス": "https://yakkun.com/legends_arceus/zukan/n46",
  "パラセクト": "https://yakkun.com/legends_arceus/zukan/n47",
  "コンパン": "https://yakkun.com/sv/zukan/n48",
  "モルフォン": "https://yakkun.com/sv/zukan/n49",
  "ディグダ": "https://yakkun.com/sv/zukan/n50",
  "ディグダ(アローラのすがた)": "https://yakkun.com/sv/zukan/n50a",
  "ダグトリオ": "https://yakkun.com/sv/zukan/n51",
  "ダグトリオ(アローラのすがた)": "https://yakkun.com/sv/zukan/n51a",
  "ニャース": "https://yakkun.com/za/zukan/n52",
  "ニャース(アローラのすがた)": "https://yakkun.com/za/zukan/n52a",
  "ニャース(ガラルのすがた)": "https://yakkun.com/za/zukan/n52g",
  "ペルシアン": "https://yakkun.com/za/zukan/n53",
  "ペルシアン(アローラのすがた)": "https://yakkun.com/za/zukan/n53a",
  "コダック": "https://yakkun.com/sv/zukan/n54",
  "ゴルダック": "https://yakkun.com/sv/zukan/n55",
  "マンキー": "https://yakkun.com/za/zukan/n56",
  "オコリザル": "https://yakkun.com/za/zukan/n57",
  "ガーディ": "https://yakkun.com/sv/zukan/n58",
  "ガーディ(ヒスイのすがた)": "https://yakkun.com/sv/zukan/n58h",
  "ウインディ": "https://yakkun.com/sv/zukan/n59",
  "ウインディ(ヒスイのすがた)": "https://yakkun.com/sv/zukan/n59h",
  "ニョロモ": "https://yakkun.com/sv/zukan/n60",
  "ニョロゾ": "https://yakkun.com/sv/zukan/n61",
  "ニョロボン": "https://yakkun.com/sv/zukan/n62",
  "ケーシィ": "https://yakkun.com/za/zukan/n63",
  "ユンゲラー": "https://yakkun.com/za/zukan/n64",
  "フーディン": "https://yakkun.com/za/zukan/n65",
  "メガフーディン": "https://yakkun.com/za/zukan/n65m",
  "ワンリキー": "https://yakkun.com/za/zukan/n66",
  "ゴーリキー": "https://yakkun.com/za/zukan/n67",
  "カイリキー": "https://yakkun.com/za/zukan/n68",
  "マダツボミ": "https://yakkun.com/za/zukan/n69",
  "ウツドン": "https://yakkun.com/za/zukan/n70",
  "ウツボット": "https://yakkun.com/za/zukan/n71",
  "メガウツボット": "https://yakkun.com/za/zukan/n71m",
  "メノクラゲ": "https://yakkun.com/sv/zukan/n72",
  "ドククラゲ": "https://yakkun.com/sv/zukan/n73",
  "イシツブテ": "https://yakkun.com/sv/zukan/n74",
  "イシツブテ(アローラのすがた)": "https://yakkun.com/sv/zukan/n74a",
  "ゴローン": "https://yakkun.com/sv/zukan/n75",
  "ゴローン(アローラのすがた)": "https://yakkun.com/sv/zukan/n75a",
  "ゴローニャ": "https://yakkun.com/sv/zukan/n76",
  "ゴローニャ(アローラのすがた)": "https://yakkun.com/sv/zukan/n76a",
  "ポニータ": "https://yakkun.com/swsh/zukan/n77",
  "ポニータ(ガラルのすがた)": "https://yakkun.com/swsh/zukan/n77g",
  "ギャロップ": "https://yakkun.com/swsh/zukan/n78",
  "ギャロップ(ガラルのすがた)": "https://yakkun.com/swsh/zukan/n78g",
  "ヤドン": "https://yakkun.com/za/zukan/n79",
  "ヤドン(ガラルのすがた)": "https://yakkun.com/za/zukan/n79g",
  "ヤドラン": "https://yakkun.com/za/zukan/n80",
  "ヤドラン(ガラルのすがた)": "https://yakkun.com/za/zukan/n80g",
  "メガヤドラン": "https://yakkun.com/za/zukan/n80m",
  "コイル": "https://yakkun.com/sv/zukan/n81",
  "レアコイル": "https://yakkun.com/sv/zukan/n82",
  "カモネギ": "https://yakkun.com/za/zukan/n83",
  "カモネギ(ガラルのすがた)": "https://yakkun.com/za/zukan/n83g",
  "ドードー": "https://yakkun.com/sv/zukan/n84",
  "ドードリオ": "https://yakkun.com/sv/zukan/n85",
  "パウワウ": "https://yakkun.com/sv/zukan/n86",
  "ジュゴン": "https://yakkun.com/sv/zukan/n87",
  "ベトベター": "https://yakkun.com/sv/zukan/n88",
  "ベトベター(アローラのすがた)": "https://yakkun.com/sv/zukan/n88a",
  "ベトベトン": "https://yakkun.com/sv/zukan/n89",
  "ベトベトン(アローラのすがた)": "https://yakkun.com/sv/zukan/n89a",
  "シェルダー": "https://yakkun.com/sv/zukan/n90",
  "パルシェン": "https://yakkun.com/sv/zukan/n91",
  "ゴース": "https://yakkun.com/za/zukan/n92",
  "ゴースト": "https://yakkun.com/za/zukan/n93",
  "ゲンガー": "https://yakkun.com/za/zukan/n94",
  "メガゲンガー": "https://yakkun.com/za/zukan/n94m",
  "イワーク": "https://yakkun.com/za/zukan/n95",
  "スリープ": "https://yakkun.com/sv/zukan/n96",
  "スリーパー": "https://yakkun.com/sv/zukan/n97",
  "クラブ": "https://yakkun.com/swsh/zukan/n98",
  "キングラー": "https://yakkun.com/swsh/zukan/n99",
  "ビリリダマ": "https://yakkun.com/sv/zukan/n100",
  "ビリリダマ(ヒスイのすがた)": "https://yakkun.com/sv/zukan/n100h",
  "マルマイン": "https://yakkun.com/sv/zukan/n101",
  "マルマイン(ヒスイのすがた)": "https://yakkun.com/sv/zukan/n101h",
  "タマタマ": "https://yakkun.com/sv/zukan/n102",
  "ナッシー": "https://yakkun.com/sv/zukan/n103",
  "ナッシー(アローラのすがた)": "https://yakkun.com/sv/zukan/n103a",
  "カラカラ": "https://yakkun.com/za/zukan/n104",
  "ガラガラ": "https://yakkun.com/za/zukan/n105",
  "ガラガラ(アローラのすがた)": "https://yakkun.com/za/zukan/n105a",
  "サワムラー": "https://yakkun.com/sv/zukan/n106",
  "エビワラー": "https://yakkun.com/sv/zukan/n107",
  "ベロリンガ": "https://yakkun.com/swsh/zukan/n108",
  "ドガース": "https://yakkun.com/sv/zukan/n109",
  "マタドガス": "https://yakkun.com/sv/zukan/n110",
  "マタドガス(ガラルのすがた)": "https://yakkun.com/sv/zukan/n110g",
  "サイホーン": "https://yakkun.com/sv/zukan/n111",
  "サイドン": "https://yakkun.com/sv/zukan/n112",
  "ラッキー": "https://yakkun.com/sv/zukan/n113",
  "モンジャラ": "https://yakkun.com/swsh/zukan/n114",
  "ガルーラ": "https://yakkun.com/za/zukan/n115",
  "メガガルーラ": "https://yakkun.com/za/zukan/n115m",
  "タッツー": "https://yakkun.com/sv/zukan/n116",
  "シードラ": "https://yakkun.com/sv/zukan/n117",
  "トサキント": "https://yakkun.com/swsh/zukan/n118",
  "アズマオウ": "https://yakkun.com/swsh/zukan/n119",
  "ヒトデマン": "https://yakkun.com/za/zukan/n120",
  "スターミー": "https://yakkun.com/za/zukan/n121",
  "メガスターミー": "https://yakkun.com/za/zukan/n121m",
  "バリヤード": "https://yakkun.com/za/zukan/n122",
  "バリヤード(ガラルのすがた)": "https://yakkun.com/za/zukan/n122g",
  "ストライク": "https://yakkun.com/za/zukan/n123",
  "ルージュラ": "https://yakkun.com/swsh/zukan/n124",
  "エレブー": "https://yakkun.com/sv/zukan/n125",
  "ブーバー": "https://yakkun.com/sv/zukan/n126",
  "カイロス": "https://yakkun.com/za/zukan/n127",
  "メガカイロス": "https://yakkun.com/za/zukan/n127m",
  "ケンタロス": "https://yakkun.com/sv/zukan/n128",
  "ケンタロス(パルデアのすがた ウォーターしゅ)": "https://yakkun.com/sv/zukan/n128c",
  "ケンタロス(パルデアのすがた コンバットしゅ)": "https://yakkun.com/sv/zukan/n128a",
  "ケンタロス(パルデアのすがた ブレイズしゅ)": "https://yakkun.com/sv/zukan/n128b",
  "コイキング": "https://yakkun.com/za/zukan/n129",
  "ギャラドス": "https://yakkun.com/za/zukan/n130",
  "メガギャラドス": "https://yakkun.com/za/zukan/n130m",
  "ラプラス": "https://yakkun.com/sv/zukan/n131",
  "メタモン": "https://yakkun.com/sv/zukan/n132",
  "イーブイ": "https://yakkun.com/za/zukan/n133",
  "シャワーズ": "https://yakkun.com/za/zukan/n134",
  "サンダース": "https://yakkun.com/za/zukan/n135",
  "ブースター": "https://yakkun.com/za/zukan/n136",
  "ポリゴン": "https://yakkun.com/za/zukan/n137",
  "オムナイト": "https://yakkun.com/swsh/zukan/n138",
  "オムスター": "https://yakkun.com/swsh/zukan/n139",
  "カブト": "https://yakkun.com/swsh/zukan/n140",
  "カブトプス": "https://yakkun.com/swsh/zukan/n141",
  "プテラ": "https://yakkun.com/za/zukan/n142",
  "メガプテラ": "https://yakkun.com/za/zukan/n142m",
  "カビゴン": "https://yakkun.com/sv/zukan/n143",
  "フリーザー": "https://yakkun.com/sv/zukan/n144",
  "フリーザー(ガラルのすがた)": "https://yakkun.com/sv/zukan/n144g",
  "サンダー": "https://yakkun.com/sv/zukan/n145",
  "サンダー(ガラルのすがた)": "https://yakkun.com/sv/zukan/n145g",
  "ファイヤー": "https://yakkun.com/sv/zukan/n146",
  "ファイヤー(ガラルのすがた)": "https://yakkun.com/sv/zukan/n146g",
  "ミニリュウ": "https://yakkun.com/za/zukan/n147",
  "ハクリュー": "https://yakkun.com/za/zukan/n148",
  "カイリュー": "https://yakkun.com/za/zukan/n149",
  "メガカイリュー": "https://yakkun.com/za/zukan/n149m",
  "ミュウツー": "https://yakkun.com/za/zukan/n150",
  "メガミュウツーＸ": "https://yakkun.com/za/zukan/n150x",
  "メガミュウツーＹ": "https://yakkun.com/za/zukan/n150y",
  "ミュウ": "https://yakkun.com/sv/zukan/n151",
  "チコリータ": "https://yakkun.com/za/zukan/n152",
  "ベイリーフ": "https://yakkun.com/za/zukan/n153",
  "メガニウム": "https://yakkun.com/za/zukan/n154",
  "メガメガニウム": "https://yakkun.com/za/zukan/n154m",
  "ヒノアラシ": "https://yakkun.com/sv/zukan/n155",
  "マグマラシ": "https://yakkun.com/sv/zukan/n156",
  "バクフーン": "https://yakkun.com/sv/zukan/n157",
  "バクフーン(ヒスイのすがた)": "https://yakkun.com/sv/zukan/n157h",
  "ワニノコ": "https://yakkun.com/za/zukan/n158",
  "アリゲイツ": "https://yakkun.com/za/zukan/n159",
  "オーダイル": "https://yakkun.com/za/zukan/n160",
  "メガオーダイル": "https://yakkun.com/za/zukan/n160m",
  "オタチ": "https://yakkun.com/sv/zukan/n161",
  "オオタチ": "https://yakkun.com/sv/zukan/n162",
  "ホーホー": "https://yakkun.com/sv/zukan/n163",
  "ヨルノズク": "https://yakkun.com/sv/zukan/n164",
  "レディバ": "https://yakkun.com/bdsp/zukan/n165",
  "レディアン": "https://yakkun.com/bdsp/zukan/n166",
  "イトマル": "https://yakkun.com/za/zukan/n167",
  "アリアドス": "https://yakkun.com/za/zukan/n168",
  "クロバット": "https://yakkun.com/za/zukan/n169",
  "チョンチー": "https://yakkun.com/sv/zukan/n170",
  "ランターン": "https://yakkun.com/sv/zukan/n171",
  "ピチュー": "https://yakkun.com/za/zukan/n172",
  "ピィ": "https://yakkun.com/za/zukan/n173",
  "ププリン": "https://yakkun.com/za/zukan/n174",
  "トゲピー": "https://yakkun.com/swsh/zukan/n175",
  "トゲチック": "https://yakkun.com/swsh/zukan/n176",
  "ネイティ": "https://yakkun.com/swsh/zukan/n177",
  "ネイティオ": "https://yakkun.com/swsh/zukan/n178",
  "メリープ": "https://yakkun.com/za/zukan/n179",
  "モココ": "https://yakkun.com/za/zukan/n180",
  "デンリュウ": "https://yakkun.com/za/zukan/n181",
  "メガデンリュウ": "https://yakkun.com/za/zukan/n181m",
  "キレイハナ": "https://yakkun.com/sv/zukan/n182",
  "マリル": "https://yakkun.com/sv/zukan/n183",
  "マリルリ": "https://yakkun.com/sv/zukan/n184",
  "ウソッキー": "https://yakkun.com/sv/zukan/n185",
  "ニョロトノ": "https://yakkun.com/sv/zukan/n186",
  "ハネッコ": "https://yakkun.com/sv/zukan/n187",
  "ポポッコ": "https://yakkun.com/sv/zukan/n188",
  "ワタッコ": "https://yakkun.com/sv/zukan/n189",
  "エイパム": "https://yakkun.com/sv/zukan/n190",
  "ヒマナッツ": "https://yakkun.com/sv/zukan/n191",
  "キマワリ": "https://yakkun.com/sv/zukan/n192",
  "ヤンヤンマ": "https://yakkun.com/sv/zukan/n193",
  "ウパー": "https://yakkun.com/sv/zukan/n194",
  "ウパー(パルデアのすがた)": "https://yakkun.com/sv/zukan/n194p",
  "ヌオー": "https://yakkun.com/sv/zukan/n195",
  "エーフィ": "https://yakkun.com/za/zukan/n196",
  "ブラッキー": "https://yakkun.com/za/zukan/n197",
  "ヤミカラス": "https://yakkun.com/sv/zukan/n198",
  "ヤドキング": "https://yakkun.com/za/zukan/n199",
  "ヤドキング(ガラルのすがた)": "https://yakkun.com/za/zukan/n199g",
  "ムウマ": "https://yakkun.com/sv/zukan/n200",
  "ソーナンス": "https://yakkun.com/swsh/zukan/n202",
  "キリンリキ": "https://yakkun.com/sv/zukan/n203",
  "クヌギダマ": "https://yakkun.com/sv/zukan/n204",
  "フォレトス": "https://yakkun.com/sv/zukan/n205",
  "ノコッチ": "https://yakkun.com/sv/zukan/n206",
  "グライガー": "https://yakkun.com/sv/zukan/n207",
  "ハガネール": "https://yakkun.com/za/zukan/n208",
  "メガハガネール": "https://yakkun.com/za/zukan/n208m",
  "ブルー": "https://yakkun.com/sv/zukan/n209",
  "グランブル": "https://yakkun.com/sv/zukan/n210",
  "ハリーセン": "https://yakkun.com/za/zukan/n211",
  "ハリーセン(ヒスイのすがた)": "https://yakkun.com/za/zukan/n211h",
  "ハッサム": "https://yakkun.com/za/zukan/n212",
  "メガハッサム": "https://yakkun.com/za/zukan/n212m",
  "ツボツボ": "https://yakkun.com/swsh/zukan/n213",
  "ヘラクロス": "https://yakkun.com/za/zukan/n214",
  "メガヘラクロス": "https://yakkun.com/za/zukan/n214m",
  "ニューラ": "https://yakkun.com/sv/zukan/n215",
  "ニューラ(ヒスイのすがた)": "https://yakkun.com/sv/zukan/n215h",
  "ヒメグマ": "https://yakkun.com/sv/zukan/n216",
  "リングマ": "https://yakkun.com/sv/zukan/n217",
  "マグマッグ": "https://yakkun.com/sv/zukan/n218",
  "マグカルゴ": "https://yakkun.com/sv/zukan/n219",
  "ウリムー": "https://yakkun.com/sv/zukan/n220",
  "イノムー": "https://yakkun.com/sv/zukan/n221",
  "サニーゴ": "https://yakkun.com/swsh/zukan/n222",
  "サニーゴ(ガラルのすがた)": "https://yakkun.com/swsh/zukan/n222g",
  "テッポウオ": "https://yakkun.com/swsh/zukan/n223",
  "オクタン": "https://yakkun.com/swsh/zukan/n224",
  "デリバード": "https://yakkun.com/za/zukan/n225",
  "マンタイン": "https://yakkun.com/swsh/zukan/n226",
  "エアームド": "https://yakkun.com/za/zukan/n227",
  "メガエアームド": "https://yakkun.com/za/zukan/n227m",
  "デルビル": "https://yakkun.com/za/zukan/n228",
  "ヘルガー": "https://yakkun.com/za/zukan/n229",
  "メガヘルガー": "https://yakkun.com/za/zukan/n229m",
  "キングドラ": "https://yakkun.com/sv/zukan/n230",
  "ゴマゾウ": "https://yakkun.com/sv/zukan/n231",
  "ドンファン": "https://yakkun.com/sv/zukan/n232",
  "ポリゴン２": "https://yakkun.com/za/zukan/n233",
  "オドシシ": "https://yakkun.com/sv/zukan/n234",
  "ドーブル": "https://yakkun.com/sv/zukan/n235",
  "バルキー": "https://yakkun.com/sv/zukan/n236",
  "カポエラー": "https://yakkun.com/sv/zukan/n237",
  "ムチュール": "https://yakkun.com/swsh/zukan/n238",
  "エレキッド": "https://yakkun.com/sv/zukan/n239",
  "ブビィ": "https://yakkun.com/sv/zukan/n240",
  "ミルタンク": "https://yakkun.com/swsh/zukan/n241",
  "ハピナス": "https://yakkun.com/sv/zukan/n242",
  "ライコウ": "https://yakkun.com/sv/zukan/n243",
  "エンテイ": "https://yakkun.com/sv/zukan/n244",
  "スイクン": "https://yakkun.com/sv/zukan/n245",
  "ヨーギラス": "https://yakkun.com/za/zukan/n246",
  "サナギラス": "https://yakkun.com/za/zukan/n247",
  "バンギラス": "https://yakkun.com/za/zukan/n248",
  "メガバンギラス": "https://yakkun.com/za/zukan/n248m",
  "ルギア": "https://yakkun.com/sv/zukan/n249",
  "ホウオウ": "https://yakkun.com/sv/zukan/n250",
  "セレビィ": "https://yakkun.com/swsh/zukan/n251",
  "キモリ": "https://yakkun.com/za/zukan/n252",
  "ジュプトル": "https://yakkun.com/za/zukan/n253",
  "ジュカイン": "https://yakkun.com/za/zukan/n254",
  "メガジュカイン": "https://yakkun.com/za/zukan/n254m",
  "アチャモ": "https://yakkun.com/za/zukan/n255",
  "ワカシャモ": "https://yakkun.com/za/zukan/n256",
  "バシャーモ": "https://yakkun.com/za/zukan/n257",
  "メガバシャーモ": "https://yakkun.com/za/zukan/n257m",
  "ミズゴロウ": "https://yakkun.com/za/zukan/n258",
  "ヌマクロー": "https://yakkun.com/za/zukan/n259",
  "ラグラージ": "https://yakkun.com/za/zukan/n260",
  "メガラグラージ": "https://yakkun.com/za/zukan/n260m",
  "ポチエナ": "https://yakkun.com/sv/zukan/n261",
  "グラエナ": "https://yakkun.com/sv/zukan/n262",
  "ジグザグマ": "https://yakkun.com/swsh/zukan/n263",
  "ジグザグマ(ガラルのすがた)": "https://yakkun.com/swsh/zukan/n263g",
  "マッスグマ": "https://yakkun.com/swsh/zukan/n264",
  "マッスグマ(ガラルのすがた)": "https://yakkun.com/swsh/zukan/n264g",
  "ケムッソ": "https://yakkun.com/legends_arceus/zukan/n265",
  "カラサリス": "https://yakkun.com/legends_arceus/zukan/n266",
  "アゲハント": "https://yakkun.com/legends_arceus/zukan/n267",
  "マユルド": "https://yakkun.com/legends_arceus/zukan/n268",
  "ドクケイル": "https://yakkun.com/legends_arceus/zukan/n269",
  "ハスボー": "https://yakkun.com/sv/zukan/n270",
  "ハスブレロ": "https://yakkun.com/sv/zukan/n271",
  "ルンパッパ": "https://yakkun.com/sv/zukan/n272",
  "タネボー": "https://yakkun.com/sv/zukan/n273",
  "コノハナ": "https://yakkun.com/sv/zukan/n274",
  "ダーテング": "https://yakkun.com/sv/zukan/n275",
  "スバメ": "https://yakkun.com/bdsp/zukan/n276",
  "オオスバメ": "https://yakkun.com/bdsp/zukan/n277",
  "キャモメ": "https://yakkun.com/sv/zukan/n278",
  "ペリッパー": "https://yakkun.com/sv/zukan/n279",
  "ラルトス": "https://yakkun.com/za/zukan/n280",
  "キルリア": "https://yakkun.com/za/zukan/n281",
  "サーナイト": "https://yakkun.com/za/zukan/n282",
  "メガサーナイト": "https://yakkun.com/za/zukan/n282m",
  "アメタマ": "https://yakkun.com/sv/zukan/n283",
  "アメモース": "https://yakkun.com/sv/zukan/n284",
  "キノココ": "https://yakkun.com/sv/zukan/n285",
  "キノガッサ": "https://yakkun.com/sv/zukan/n286",
  "ナマケロ": "https://yakkun.com/sv/zukan/n287",
  "ヤルキモノ": "https://yakkun.com/sv/zukan/n288",
  "ケッキング": "https://yakkun.com/sv/zukan/n289",
  "ツチニン": "https://yakkun.com/swsh/zukan/n290",
  "テッカニン": "https://yakkun.com/swsh/zukan/n291",
  "ヌケニン": "https://yakkun.com/swsh/zukan/n292",
  "ゴニョニョ": "https://yakkun.com/swsh/zukan/n293",
  "ドゴーム": "https://yakkun.com/swsh/zukan/n294",
  "バクオング": "https://yakkun.com/swsh/zukan/n295",
  "マクノシタ": "https://yakkun.com/sv/zukan/n296",
  "ハリテヤマ": "https://yakkun.com/sv/zukan/n297",
  "ルリリ": "https://yakkun.com/sv/zukan/n298",
  "ノズパス": "https://yakkun.com/sv/zukan/n299",
  "エネコ": "https://yakkun.com/bdsp/zukan/n300",
  "エネコロロ": "https://yakkun.com/bdsp/zukan/n301",
  "ヤミラミ": "https://yakkun.com/za/zukan/n302",
  "メガヤミラミ": "https://yakkun.com/za/zukan/n302m",
  "クチート": "https://yakkun.com/za/zukan/n303",
  "メガクチート": "https://yakkun.com/za/zukan/n303m",
  "ココドラ": "https://yakkun.com/za/zukan/n304",
  "コドラ": "https://yakkun.com/za/zukan/n305",
  "ボスゴドラ": "https://yakkun.com/za/zukan/n306",
  "メガボスゴドラ": "https://yakkun.com/za/zukan/n306m",
  "アサナン": "https://yakkun.com/za/zukan/n307",
  "チャーレム": "https://yakkun.com/za/zukan/n308",
  "メガチャーレム": "https://yakkun.com/za/zukan/n308m",
  "ラクライ": "https://yakkun.com/za/zukan/n309",
  "ライボルト": "https://yakkun.com/za/zukan/n310",
  "メガライボルト": "https://yakkun.com/za/zukan/n310m",
  "プラスル": "https://yakkun.com/sv/zukan/n311",
  "マイナン": "https://yakkun.com/sv/zukan/n312",
  "バルビート": "https://yakkun.com/sv/zukan/n313",
  "イルミーゼ": "https://yakkun.com/sv/zukan/n314",
  "ロゼリア": "https://yakkun.com/za/zukan/n315",
  "ゴクリン": "https://yakkun.com/za/zukan/n316",
  "マルノーム": "https://yakkun.com/za/zukan/n317",
  "キバニア": "https://yakkun.com/za/zukan/n318",
  "サメハダー": "https://yakkun.com/za/zukan/n319",
  "メガサメハダー": "https://yakkun.com/za/zukan/n319m",
  "ホエルコ": "https://yakkun.com/swsh/zukan/n320",
  "ホエルオー": "https://yakkun.com/swsh/zukan/n321",
  "ドンメル": "https://yakkun.com/za/zukan/n322",
  "バクーダ": "https://yakkun.com/za/zukan/n323",
  "メガバクーダ": "https://yakkun.com/za/zukan/n323m",
  "コータス": "https://yakkun.com/sv/zukan/n324",
  "バネブー": "https://yakkun.com/za/zukan/n325",
  "ブーピッグ": "https://yakkun.com/za/zukan/n326",
  "パッチール": "https://yakkun.com/bdsp/zukan/n327",
  "ナックラー": "https://yakkun.com/sv/zukan/n328",
  "ビブラーバ": "https://yakkun.com/sv/zukan/n329",
  "フライゴン": "https://yakkun.com/sv/zukan/n330",
  "サボネア": "https://yakkun.com/sv/zukan/n331",
  "ノクタス": "https://yakkun.com/sv/zukan/n332",
  "チルット": "https://yakkun.com/za/zukan/n333",
  "チルタリス": "https://yakkun.com/za/zukan/n334",
  "メガチルタリス": "https://yakkun.com/za/zukan/n334m",
  "ザングース": "https://yakkun.com/za/zukan/n335",
  "ハブネーク": "https://yakkun.com/za/zukan/n336",
  "ルナトーン": "https://yakkun.com/swsh/zukan/n337",
  "ソルロック": "https://yakkun.com/swsh/zukan/n338",
  "ドジョッチ": "https://yakkun.com/sv/zukan/n339",
  "ナマズン": "https://yakkun.com/sv/zukan/n340",
  "ヘイガニ": "https://yakkun.com/sv/zukan/n341",
  "シザリガー": "https://yakkun.com/sv/zukan/n342",
  "ヤジロン": "https://yakkun.com/swsh/zukan/n343",
  "ネンドール": "https://yakkun.com/swsh/zukan/n344",
  "リリーラ": "https://yakkun.com/swsh/zukan/n345",
  "ユレイドル": "https://yakkun.com/swsh/zukan/n346",
  "アノプス": "https://yakkun.com/swsh/zukan/n347",
  "アーマルド": "https://yakkun.com/swsh/zukan/n348",
  "ヒンバス": "https://yakkun.com/za/zukan/n349",
  "ミロカロス": "https://yakkun.com/za/zukan/n350",
  "カクレオン": "https://yakkun.com/za/zukan/n352",
  "カゲボウズ": "https://yakkun.com/za/zukan/n353",
  "ジュペッタ": "https://yakkun.com/za/zukan/n354",
  "メガジュペッタ": "https://yakkun.com/za/zukan/n354m",
  "ヨマワル": "https://yakkun.com/sv/zukan/n355",
  "サマヨール": "https://yakkun.com/sv/zukan/n356",
  "トロピウス": "https://yakkun.com/sv/zukan/n357",
  "チリーン": "https://yakkun.com/za/zukan/n358",
  "アブソル": "https://yakkun.com/za/zukan/n359",
  "メガアブソル": "https://yakkun.com/za/zukan/n359m",
  "ソーナノ": "https://yakkun.com/swsh/zukan/n360",
  "ユキワラシ": "https://yakkun.com/za/zukan/n361",
  "オニゴーリ": "https://yakkun.com/za/zukan/n362",
  "メガオニゴーリ": "https://yakkun.com/za/zukan/n362m",
  "タマザラシ": "https://yakkun.com/swsh/zukan/n363",
  "トドグラー": "https://yakkun.com/swsh/zukan/n364",
  "トドゼルガ": "https://yakkun.com/swsh/zukan/n365",
  "パールル": "https://yakkun.com/bdsp/zukan/n366",
  "ハンテール": "https://yakkun.com/bdsp/zukan/n367",
  "サクラビス": "https://yakkun.com/bdsp/zukan/n368",
  "ジーランス": "https://yakkun.com/swsh/zukan/n369",
  "ラブカス": "https://yakkun.com/sv/zukan/n370",
  "タツベイ": "https://yakkun.com/za/zukan/n371",
  "コモルー": "https://yakkun.com/za/zukan/n372",
  "ボーマンダ": "https://yakkun.com/za/zukan/n373",
  "メガボーマンダ": "https://yakkun.com/za/zukan/n373m",
  "ダンバル": "https://yakkun.com/za/zukan/n374",
  "メタング": "https://yakkun.com/za/zukan/n375",
  "メタグロス": "https://yakkun.com/za/zukan/n376",
  "メガメタグロス": "https://yakkun.com/za/zukan/n376m",
  "レジロック": "https://yakkun.com/sv/zukan/n377",
  "レジアイス": "https://yakkun.com/sv/zukan/n378",
  "レジスチル": "https://yakkun.com/sv/zukan/n379",
  "ラティアス": "https://yakkun.com/za/zukan/n380",
  "メガラティアス": "https://yakkun.com/za/zukan/n380m",
  "ラティオス": "https://yakkun.com/za/zukan/n381",
  "メガラティオス": "https://yakkun.com/za/zukan/n381m",
  "カイオーガ": "https://yakkun.com/za/zukan/n382",
  "グラードン": "https://yakkun.com/za/zukan/n383",
  "レックウザ": "https://yakkun.com/za/zukan/n384",
  "メガレックウザ": "https://yakkun.com/za/zukan/n384m",
  "ジラーチ": "https://yakkun.com/sv/zukan/n385",
  "デオキシス(アタックフォルム)": "https://yakkun.com/sv/zukan/n386a",
  "デオキシス(スピードフォルム)": "https://yakkun.com/sv/zukan/n386s",
  "デオキシス(ディフェンスフォルム)": "https://yakkun.com/sv/zukan/n386d",
  "デオキシス(ノーマルフォルム)": "https://yakkun.com/sv/zukan/n386",
  "ナエトル": "https://yakkun.com/sv/zukan/n387",
  "ハヤシガメ": "https://yakkun.com/sv/zukan/n388",
  "ドダイトス": "https://yakkun.com/sv/zukan/n389",
  "ヒコザル": "https://yakkun.com/sv/zukan/n390",
  "モウカザル": "https://yakkun.com/sv/zukan/n391",
  "ゴウカザル": "https://yakkun.com/sv/zukan/n392",
  "ポッチャマ": "https://yakkun.com/sv/zukan/n393",
  "ポッタイシ": "https://yakkun.com/sv/zukan/n394",
  "エンペルト": "https://yakkun.com/sv/zukan/n395",
  "ムックル": "https://yakkun.com/za/zukan/n396",
  "ムクバード": "https://yakkun.com/za/zukan/n397",
  "ムクホーク": "https://yakkun.com/za/zukan/n398",
  "ビッパ": "https://yakkun.com/legends_arceus/zukan/n399",
  "ビーダル": "https://yakkun.com/legends_arceus/zukan/n400",
  "コロボーシ": "https://yakkun.com/sv/zukan/n401",
  "コロトック": "https://yakkun.com/sv/zukan/n402",
  "コリンク": "https://yakkun.com/sv/zukan/n403",
  "ルクシオ": "https://yakkun.com/sv/zukan/n404",
  "レントラー": "https://yakkun.com/sv/zukan/n405",
  "スボミー": "https://yakkun.com/za/zukan/n406",
  "ロズレイド": "https://yakkun.com/za/zukan/n407",
  "ズガイドス": "https://yakkun.com/sv/zukan/n408",
  "ラムパルド": "https://yakkun.com/sv/zukan/n409",
  "タテトプス": "https://yakkun.com/sv/zukan/n410",
  "トリデプス": "https://yakkun.com/sv/zukan/n411",
  "ミノマダム(くさきのミノ)": "https://yakkun.com/legends_arceus/zukan/n413",
  "ミノマダム(ゴミのミノ)": "https://yakkun.com/legends_arceus/zukan/n413d",
  "ミノマダム(すなちのミノ)": "https://yakkun.com/legends_arceus/zukan/n413s",
  "ガーメイル": "https://yakkun.com/legends_arceus/zukan/n414",
  "ミツハニー": "https://yakkun.com/sv/zukan/n415",
  "ビークイン": "https://yakkun.com/sv/zukan/n416",
  "パチリス": "https://yakkun.com/sv/zukan/n417",
  "ブイゼル": "https://yakkun.com/sv/zukan/n418",
  "フローゼル": "https://yakkun.com/sv/zukan/n419",
  "チェリンボ": "https://yakkun.com/swsh/zukan/n420",
  "エテボース": "https://yakkun.com/sv/zukan/n424",
  "フワンテ": "https://yakkun.com/sv/zukan/n425",
  "フワライド": "https://yakkun.com/sv/zukan/n426",
  "ミミロル": "https://yakkun.com/za/zukan/n427",
  "ミミロップ": "https://yakkun.com/za/zukan/n428",
  "メガミミロップ": "https://yakkun.com/za/zukan/n428m",
  "ムウマージ": "https://yakkun.com/sv/zukan/n429",
  "ドンカラス": "https://yakkun.com/sv/zukan/n430",
  "ニャルマー": "https://yakkun.com/legends_arceus/zukan/n431",
  "ブニャット": "https://yakkun.com/legends_arceus/zukan/n432",
  "リーシャン": "https://yakkun.com/za/zukan/n433",
  "スカンプー": "https://yakkun.com/sv/zukan/n434",
  "スカタンク": "https://yakkun.com/sv/zukan/n435",
  "ドーミラー": "https://yakkun.com/sv/zukan/n436",
  "ドータクン": "https://yakkun.com/sv/zukan/n437",
  "ウソハチ": "https://yakkun.com/sv/zukan/n438",
  "マネネ": "https://yakkun.com/za/zukan/n439",
  "ピンプク": "https://yakkun.com/sv/zukan/n440",
  "ペラップ": "https://yakkun.com/legends_arceus/zukan/n441",
  "ミカルゲ": "https://yakkun.com/sv/zukan/n442",
  "フカマル": "https://yakkun.com/za/zukan/n443",
  "ガバイト": "https://yakkun.com/za/zukan/n444",
  "ガブリアス": "https://yakkun.com/za/zukan/n445",
  "メガガブリアス": "https://yakkun.com/za/zukan/n445m",
  "ゴンベ": "https://yakkun.com/sv/zukan/n446",
  "リオル": "https://yakkun.com/za/zukan/n447",
  "ルカリオ": "https://yakkun.com/za/zukan/n448",
  "メガルカリオ": "https://yakkun.com/za/zukan/n448m",
  "ヒポポタス": "https://yakkun.com/za/zukan/n449",
  "カバルドン": "https://yakkun.com/za/zukan/n450",
  "スコルピ": "https://yakkun.com/swsh/zukan/n451",
  "ドラピオン": "https://yakkun.com/swsh/zukan/n452",
  "グレッグル": "https://yakkun.com/sv/zukan/n453",
  "ドクロッグ": "https://yakkun.com/sv/zukan/n454",
  "マスキッパ": "https://yakkun.com/legends_arceus/zukan/n455",
  "ケイコウオ": "https://yakkun.com/sv/zukan/n456",
  "ネオラント": "https://yakkun.com/sv/zukan/n457",
  "タマンタ": "https://yakkun.com/swsh/zukan/n458",
  "ユキカブリ": "https://yakkun.com/za/zukan/n459",
  "ユキノオー": "https://yakkun.com/za/zukan/n460",
  "メガユキノオー": "https://yakkun.com/za/zukan/n460m",
  "マニューラ": "https://yakkun.com/sv/zukan/n461",
  "ジバコイル": "https://yakkun.com/sv/zukan/n462",
  "ベロベルト": "https://yakkun.com/swsh/zukan/n463",
  "ドサイドン": "https://yakkun.com/sv/zukan/n464",
  "モジャンボ": "https://yakkun.com/swsh/zukan/n465",
  "エレキブル": "https://yakkun.com/sv/zukan/n466",
  "ブーバーン": "https://yakkun.com/sv/zukan/n467",
  "トゲキッス": "https://yakkun.com/swsh/zukan/n468",
  "メガヤンマ": "https://yakkun.com/sv/zukan/n469",
  "リーフィア": "https://yakkun.com/za/zukan/n470",
  "グレイシア": "https://yakkun.com/za/zukan/n471",
  "グライオン": "https://yakkun.com/sv/zukan/n472",
  "マンムー": "https://yakkun.com/sv/zukan/n473",
  "ポリゴンＺ": "https://yakkun.com/za/zukan/n474",
  "エルレイド": "https://yakkun.com/za/zukan/n475",
  "メガエルレイド": "https://yakkun.com/za/zukan/n475m",
  "ダイノーズ": "https://yakkun.com/sv/zukan/n476",
  "ヨノワール": "https://yakkun.com/sv/zukan/n477",
  "ユキメノコ": "https://yakkun.com/za/zukan/n478",
  "メガユキメノコ": "https://yakkun.com/za/zukan/n478m",
  "ロトム(ウォッシュロトム)": "https://yakkun.com/za/zukan/n479w",
  "ロトム(カットロトム)": "https://yakkun.com/za/zukan/n479c",
  "ロトム(スピンロトム)": "https://yakkun.com/za/zukan/n479s",
  "ロトム(ヒートロトム)": "https://yakkun.com/za/zukan/n479h",
  "ロトム(フロストロトム)": "https://yakkun.com/za/zukan/n479f",
  "ロトム": "https://yakkun.com/za/zukan/n479",
  "ユクシー": "https://yakkun.com/sv/zukan/n480",
  "エムリット": "https://yakkun.com/sv/zukan/n481",
  "アグノム": "https://yakkun.com/sv/zukan/n482",
  "ディアルガ": "https://yakkun.com/sv/zukan/n483",
  "ディアルガ(オリジンフォルム)": "https://yakkun.com/sv/zukan/n483o",
  "パルキア": "https://yakkun.com/sv/zukan/n484",
  "パルキア(オリジンフォルム)": "https://yakkun.com/sv/zukan/n484o",
  "ヒードラン": "https://yakkun.com/za/zukan/n485",
  "レジギガス": "https://yakkun.com/sv/zukan/n486",
  "ギラティナ(アナザーフォルム)": "https://yakkun.com/sv/zukan/n487",
  "ギラティナ(オリジンフォルム)": "https://yakkun.com/sv/zukan/n487o",
  "クレセリア": "https://yakkun.com/sv/zukan/n488",
  "フィオネ": "https://yakkun.com/sv/zukan/n489",
  "マナフィ": "https://yakkun.com/sv/zukan/n490",
  "ダークライ": "https://yakkun.com/za/zukan/n491",
  "シェイミ(スカイフォルム)": "https://yakkun.com/sv/zukan/n492s",
  "シェイミ(ランドフォルム)": "https://yakkun.com/sv/zukan/n492",
  "アルセウス": "https://yakkun.com/sv/zukan/n493",
  "ビクティニ": "https://yakkun.com/swsh/zukan/n494",
  "ツタージャ": "https://yakkun.com/sv/zukan/n495",
  "ジャノビー": "https://yakkun.com/sv/zukan/n496",
  "ジャローダ": "https://yakkun.com/sv/zukan/n497",
  "ポカブ": "https://yakkun.com/za/zukan/n498",
  "チャオブー": "https://yakkun.com/za/zukan/n499",
  "エンブオー": "https://yakkun.com/za/zukan/n500",
  "メガエンブオー": "https://yakkun.com/za/zukan/n500m",
  "ミジュマル": "https://yakkun.com/sv/zukan/n501",
  "フタチマル": "https://yakkun.com/sv/zukan/n502",
  "ダイケンキ": "https://yakkun.com/sv/zukan/n503",
  "ダイケンキ(ヒスイのすがた)": "https://yakkun.com/sv/zukan/n503h",
  "ミネズミ": "https://yakkun.com/za/zukan/n504",
  "ミルホッグ": "https://yakkun.com/za/zukan/n505",
  "ヨーテリー": "https://yakkun.com/swsh/zukan/n506",
  "ハーデリア": "https://yakkun.com/swsh/zukan/n507",
  "ムーランド": "https://yakkun.com/swsh/zukan/n508",
  "チョロネコ": "https://yakkun.com/za/zukan/n509",
  "レパルダス": "https://yakkun.com/za/zukan/n510",
  "ヤナップ": "https://yakkun.com/za/zukan/n511",
  "ヤナッキー": "https://yakkun.com/za/zukan/n512",
  "バオップ": "https://yakkun.com/za/zukan/n513",
  "バオッキー": "https://yakkun.com/za/zukan/n514",
  "ヒヤップ": "https://yakkun.com/za/zukan/n515",
  "ヒヤッキー": "https://yakkun.com/za/zukan/n516",
  "ムンナ": "https://yakkun.com/za/zukan/n517",
  "ムシャーナ": "https://yakkun.com/za/zukan/n518",
  "マメパト": "https://yakkun.com/swsh/zukan/n519",
  "ハトーボー": "https://yakkun.com/swsh/zukan/n520",
  "ケンホロウ": "https://yakkun.com/swsh/zukan/n521",
  "シママ": "https://yakkun.com/sv/zukan/n522",
  "ゼブライカ": "https://yakkun.com/sv/zukan/n523",
  "ダンゴロ": "https://yakkun.com/swsh/zukan/n524",
  "ガントル": "https://yakkun.com/swsh/zukan/n525",
  "ギガイアス": "https://yakkun.com/swsh/zukan/n526",
  "コロモリ": "https://yakkun.com/swsh/zukan/n527",
  "ココロモリ": "https://yakkun.com/swsh/zukan/n528",
  "モグリュー": "https://yakkun.com/za/zukan/n529",
  "ドリュウズ": "https://yakkun.com/za/zukan/n530",
  "メガドリュウズ": "https://yakkun.com/za/zukan/n530m",
  "タブンネ": "https://yakkun.com/za/zukan/n531",
  "メガタブンネ": "https://yakkun.com/za/zukan/n531m",
  "ドッコラー": "https://yakkun.com/sv/zukan/n532",
  "ドテッコツ": "https://yakkun.com/sv/zukan/n533",
  "ローブシン": "https://yakkun.com/sv/zukan/n534",
  "オタマロ": "https://yakkun.com/swsh/zukan/n535",
  "ガマガル": "https://yakkun.com/swsh/zukan/n536",
  "ガマゲロゲ": "https://yakkun.com/swsh/zukan/n537",
  "ナゲキ": "https://yakkun.com/za/zukan/n538",
  "ダゲキ": "https://yakkun.com/za/zukan/n539",
  "クルミル": "https://yakkun.com/sv/zukan/n540",
  "クルマユ": "https://yakkun.com/sv/zukan/n541",
  "ハハコモリ": "https://yakkun.com/sv/zukan/n542",
  "フシデ": "https://yakkun.com/za/zukan/n543",
  "ホイーガ": "https://yakkun.com/za/zukan/n544",
  "ペンドラー": "https://yakkun.com/za/zukan/n545",
  "メガペンドラー": "https://yakkun.com/za/zukan/n545m",
  "モンメン": "https://yakkun.com/sv/zukan/n546",
  "エルフーン": "https://yakkun.com/sv/zukan/n547",
  "チュリネ": "https://yakkun.com/sv/zukan/n548",
  "ドレディア": "https://yakkun.com/sv/zukan/n549",
  "ドレディア(ヒスイのすがた)": "https://yakkun.com/sv/zukan/n549h",
  "バスラオ(あおすじのすがた)": "https://yakkun.com/sv/zukan/n550f",
  "バスラオ(あかすじのすがた)": "https://yakkun.com/sv/zukan/n550",
  "バスラオ(しろすじのすがた)": "https://yakkun.com/sv/zukan/n550w",
  "メグロコ": "https://yakkun.com/za/zukan/n551",
  "ワルビル": "https://yakkun.com/za/zukan/n552",
  "ワルビアル": "https://yakkun.com/za/zukan/n553",
  "ダルマッカ": "https://yakkun.com/swsh/zukan/n554",
  "ダルマッカ(ガラルのすがた)": "https://yakkun.com/swsh/zukan/n554g",
  "ヒヒダルマ(ガラルのすがた ダルマモード)": "https://yakkun.com/swsh/zukan/n555h",
  "ヒヒダルマ(ガラルのすがた ノーマルモード)": "https://yakkun.com/swsh/zukan/n555g",
  "ヒヒダルマ(ダルマモード)": "https://yakkun.com/swsh/zukan/n555f",
  "ヒヒダルマ(ノーマルモード)": "https://yakkun.com/swsh/zukan/n555",
  "マラカッチ": "https://yakkun.com/swsh/zukan/n556",
  "イシズマイ": "https://yakkun.com/swsh/zukan/n557",
  "イワパレス": "https://yakkun.com/swsh/zukan/n558",
  "ズルッグ": "https://yakkun.com/za/zukan/n559",
  "ズルズキン": "https://yakkun.com/za/zukan/n560",
  "メガズルズキン": "https://yakkun.com/za/zukan/n560m",
  "シンボラー": "https://yakkun.com/swsh/zukan/n561",
  "デスマス": "https://yakkun.com/za/zukan/n562",
  "デスマス(ガラルのすがた)": "https://yakkun.com/za/zukan/n562g",
  "デスカーン": "https://yakkun.com/za/zukan/n563",
  "プロトーガ": "https://yakkun.com/swsh/zukan/n564",
  "アバゴーラ": "https://yakkun.com/swsh/zukan/n565",
  "アーケン": "https://yakkun.com/swsh/zukan/n566",
  "アーケオス": "https://yakkun.com/swsh/zukan/n567",
  "ヤブクロン": "https://yakkun.com/za/zukan/n568",
  "ダストダス": "https://yakkun.com/za/zukan/n569",
  "ゾロア": "https://yakkun.com/sv/zukan/n570",
  "ゾロア(ヒスイのすがた)": "https://yakkun.com/sv/zukan/n570h",
  "ゾロアーク": "https://yakkun.com/sv/zukan/n571",
  "ゾロアーク(ヒスイのすがた)": "https://yakkun.com/sv/zukan/n571h",
  "チラーミィ": "https://yakkun.com/sv/zukan/n572",
  "チラチーノ": "https://yakkun.com/sv/zukan/n573",
  "ゴチム": "https://yakkun.com/sv/zukan/n574",
  "ゴチミル": "https://yakkun.com/sv/zukan/n575",
  "ゴチルゼル": "https://yakkun.com/sv/zukan/n576",
  "ユニラン": "https://yakkun.com/sv/zukan/n577",
  "ダブラン": "https://yakkun.com/sv/zukan/n578",
  "ランクルス": "https://yakkun.com/sv/zukan/n579",
  "コアルヒー": "https://yakkun.com/sv/zukan/n580",
  "スワンナ": "https://yakkun.com/sv/zukan/n581",
  "バニプッチ": "https://yakkun.com/za/zukan/n582",
  "バニリッチ": "https://yakkun.com/za/zukan/n583",
  "バイバニラ": "https://yakkun.com/za/zukan/n584",
  "エモンガ": "https://yakkun.com/za/zukan/n587",
  "カブルモ": "https://yakkun.com/swsh/zukan/n588",
  "シュバルゴ": "https://yakkun.com/swsh/zukan/n589",
  "タマゲタケ": "https://yakkun.com/za/zukan/n590",
  "モロバレル": "https://yakkun.com/za/zukan/n591",
  "プルリル": "https://yakkun.com/swsh/zukan/n592",
  "ブルンゲル": "https://yakkun.com/swsh/zukan/n593",
  "ママンボウ": "https://yakkun.com/sv/zukan/n594",
  "バチュル": "https://yakkun.com/sv/zukan/n595",
  "デンチュラ": "https://yakkun.com/sv/zukan/n596",
  "テッシード": "https://yakkun.com/swsh/zukan/n597",
  "ナットレイ": "https://yakkun.com/swsh/zukan/n598",
  "ギアル": "https://yakkun.com/swsh/zukan/n599",
  "ギギアル": "https://yakkun.com/swsh/zukan/n600",
  "ギギギアル": "https://yakkun.com/swsh/zukan/n601",
  "シビシラス": "https://yakkun.com/za/zukan/n602",
  "シビビール": "https://yakkun.com/za/zukan/n603",
  "シビルドン": "https://yakkun.com/za/zukan/n604",
  "メガシビルドン": "https://yakkun.com/za/zukan/n604m",
  "リグレー": "https://yakkun.com/swsh/zukan/n605",
  "オーベム": "https://yakkun.com/swsh/zukan/n606",
  "ヒトモシ": "https://yakkun.com/za/zukan/n607",
  "ランプラー": "https://yakkun.com/za/zukan/n608",
  "シャンデラ": "https://yakkun.com/za/zukan/n609",
  "メガシャンデラ": "https://yakkun.com/za/zukan/n609m",
  "キバゴ": "https://yakkun.com/sv/zukan/n610",
  "オノンド": "https://yakkun.com/sv/zukan/n611",
  "オノノクス": "https://yakkun.com/sv/zukan/n612",
  "クマシュン": "https://yakkun.com/sv/zukan/n613",
  "ツンベアー": "https://yakkun.com/sv/zukan/n614",
  "フリージオ": "https://yakkun.com/za/zukan/n615",
  "チョボマキ": "https://yakkun.com/swsh/zukan/n616",
  "アギルダー": "https://yakkun.com/swsh/zukan/n617",
  "マッギョ": "https://yakkun.com/za/zukan/n618",
  "マッギョ(ガラルのすがた)": "https://yakkun.com/za/zukan/n618g",
  "コジョフー": "https://yakkun.com/sv/zukan/n619",
  "コジョンド": "https://yakkun.com/sv/zukan/n620",
  "クリムガン": "https://yakkun.com/swsh/zukan/n621",
  "ゴビット": "https://yakkun.com/za/zukan/n622",
  "ゴルーグ": "https://yakkun.com/za/zukan/n623",
  "コマタナ": "https://yakkun.com/sv/zukan/n624",
  "キリキザン": "https://yakkun.com/sv/zukan/n625",
  "バッフロン": "https://yakkun.com/swsh/zukan/n626",
  "ワシボン": "https://yakkun.com/sv/zukan/n627",
  "ウォーグル": "https://yakkun.com/sv/zukan/n628",
  "ウォーグル(ヒスイのすがた)": "https://yakkun.com/sv/zukan/n628h",
  "バルチャイ": "https://yakkun.com/sv/zukan/n629",
  "バルジーナ": "https://yakkun.com/sv/zukan/n630",
  "クイタラン": "https://yakkun.com/swsh/zukan/n631",
  "アイアント": "https://yakkun.com/swsh/zukan/n632",
  "モノズ": "https://yakkun.com/sv/zukan/n633",
  "ジヘッド": "https://yakkun.com/sv/zukan/n634",
  "サザンドラ": "https://yakkun.com/sv/zukan/n635",
  "メラルバ": "https://yakkun.com/sv/zukan/n636",
  "ウルガモス": "https://yakkun.com/sv/zukan/n637",
  "コバルオン": "https://yakkun.com/za/zukan/n638",
  "テラキオン": "https://yakkun.com/za/zukan/n639",
  "ビリジオン": "https://yakkun.com/za/zukan/n640",
  "トルネロス(けしんフォルム)": "https://yakkun.com/sv/zukan/n641",
  "トルネロス(れいじゅうフォルム)": "https://yakkun.com/sv/zukan/n641a",
  "ボルトロス(けしんフォルム)": "https://yakkun.com/sv/zukan/n642",
  "ボルトロス(れいじゅうフォルム)": "https://yakkun.com/sv/zukan/n642a",
  "レシラム": "https://yakkun.com/sv/zukan/n643",
  "ゼクロム": "https://yakkun.com/sv/zukan/n644",
  "ランドロス(けしんフォルム)": "https://yakkun.com/sv/zukan/n645",
  "ランドロス(れいじゅうフォルム)": "https://yakkun.com/sv/zukan/n645a",
  "キュレム": "https://yakkun.com/sv/zukan/n646",
  "キュレム(ブラックキュレム)": "https://yakkun.com/sv/zukan/n646b",
  "キュレム(ホワイトキュレム)": "https://yakkun.com/sv/zukan/n646w",
  "ケルディオ(いつものすがた)": "https://yakkun.com/za/zukan/n647",
  "ケルディオ(かくごのすがた)": "https://yakkun.com/za/zukan/n647k",
  "メロエッタ(ステップフォルム)": "https://yakkun.com/za/zukan/n648f",
  "メロエッタ(ボイスフォルム)": "https://yakkun.com/za/zukan/n648",
  "ハリマロン": "https://yakkun.com/za/zukan/n650",
  "ハリボーグ": "https://yakkun.com/za/zukan/n651",
  "ブリガロン": "https://yakkun.com/za/zukan/n652",
  "メガブリガロン": "https://yakkun.com/za/zukan/n652m",
  "フォッコ": "https://yakkun.com/za/zukan/n653",
  "テールナー": "https://yakkun.com/za/zukan/n654",
  "マフォクシー": "https://yakkun.com/za/zukan/n655",
  "メガマフォクシー": "https://yakkun.com/za/zukan/n655m",
  "ケロマツ": "https://yakkun.com/za/zukan/n656",
  "ゲコガシラ": "https://yakkun.com/za/zukan/n657",
  "ゲッコウガ": "https://yakkun.com/za/zukan/n658",
  "ゲッコウガ(サトシゲッコウガ)": "https://yakkun.com/sm/zukan/n658f",
  "メガゲッコウガ": "https://yakkun.com/za/zukan/n658m",
  "ホルビー": "https://yakkun.com/za/zukan/n659",
  "ホルード": "https://yakkun.com/za/zukan/n660",
  "ヤヤコマ": "https://yakkun.com/za/zukan/n661",
  "ヒノヤコマ": "https://yakkun.com/za/zukan/n662",
  "ファイアロー": "https://yakkun.com/za/zukan/n663",
  "コフキムシ": "https://yakkun.com/za/zukan/n664",
  "コフーライ": "https://yakkun.com/za/zukan/n665",
  "シシコ": "https://yakkun.com/za/zukan/n667",
  "カエンジシ": "https://yakkun.com/za/zukan/n668",
  "メガカエンジシ": "https://yakkun.com/za/zukan/n668m",
  "メェークル": "https://yakkun.com/za/zukan/n672",
  "ゴーゴート": "https://yakkun.com/za/zukan/n673",
  "ヤンチャム": "https://yakkun.com/za/zukan/n674",
  "ゴロンダ": "https://yakkun.com/za/zukan/n675",
  "ニャスパー": "https://yakkun.com/za/zukan/n677",
  "ニャオニクス(オスのすがた)": "https://yakkun.com/za/zukan/n678",
  "ニャオニクス(メスのすがた)": "https://yakkun.com/za/zukan/n678f",
  "ヒトツキ": "https://yakkun.com/za/zukan/n679",
  "ニダンギル": "https://yakkun.com/za/zukan/n680",
  "ギルガルド(シールドフォルム)": "https://yakkun.com/za/zukan/n681",
  "ギルガルド(ブレードフォルム)": "https://yakkun.com/za/zukan/n681b",
  "シュシュプ": "https://yakkun.com/za/zukan/n682",
  "フレフワン": "https://yakkun.com/za/zukan/n683",
  "ペロッパフ": "https://yakkun.com/za/zukan/n684",
  "ペロリーム": "https://yakkun.com/za/zukan/n685",
  "マーイーカ": "https://yakkun.com/za/zukan/n686",
  "カラマネロ": "https://yakkun.com/za/zukan/n687",
  "メガカラマネロ": "https://yakkun.com/za/zukan/n687m",
  "カメテテ": "https://yakkun.com/za/zukan/n688",
  "ガメノデス": "https://yakkun.com/za/zukan/n689",
  "メガガメノデス": "https://yakkun.com/za/zukan/n689m",
  "クズモー": "https://yakkun.com/za/zukan/n690",
  "ドラミドロ": "https://yakkun.com/za/zukan/n691",
  "メガドラミドロ": "https://yakkun.com/za/zukan/n691m",
  "ウデッポウ": "https://yakkun.com/za/zukan/n692",
  "ブロスター": "https://yakkun.com/za/zukan/n693",
  "エリキテル": "https://yakkun.com/za/zukan/n694",
  "エレザード": "https://yakkun.com/za/zukan/n695",
  "チゴラス": "https://yakkun.com/za/zukan/n696",
  "ガチゴラス": "https://yakkun.com/za/zukan/n697",
  "アマルス": "https://yakkun.com/za/zukan/n698",
  "アマルルガ": "https://yakkun.com/za/zukan/n699",
  "ニンフィア": "https://yakkun.com/za/zukan/n700",
  "ルチャブル": "https://yakkun.com/za/zukan/n701",
  "メガルチャブル": "https://yakkun.com/za/zukan/n701m",
  "デデンネ": "https://yakkun.com/za/zukan/n702",
  "メレシー": "https://yakkun.com/za/zukan/n703",
  "ヌメラ": "https://yakkun.com/za/zukan/n704",
  "ヌメイル": "https://yakkun.com/za/zukan/n705",
  "ヌメイル(ヒスイのすがた)": "https://yakkun.com/za/zukan/n705h",
  "ヌメルゴン": "https://yakkun.com/za/zukan/n706",
  "ヌメルゴン(ヒスイのすがた)": "https://yakkun.com/za/zukan/n706h",
  "クレッフィ": "https://yakkun.com/za/zukan/n707",
  "ボクレー": "https://yakkun.com/za/zukan/n708",
  "オーロット": "https://yakkun.com/za/zukan/n709",
  "バケッチャ(おおきいサイズ)": "https://yakkun.com/za/zukan/n710l",
  "バケッチャ(ちいさいサイズ)": "https://yakkun.com/za/zukan/n710s",
  "バケッチャ(とくだいサイズ)": "https://yakkun.com/za/zukan/n710k",
  "バケッチャ(ふつうのサイズ)": "https://yakkun.com/za/zukan/n710",
  "パンプジン(おおきいサイズ)": "https://yakkun.com/za/zukan/n711l",
  "パンプジン(ちいさいサイズ)": "https://yakkun.com/za/zukan/n711s",
  "パンプジン(とくだいサイズ)": "https://yakkun.com/za/zukan/n711k",
  "パンプジン(ふつうのサイズ)": "https://yakkun.com/za/zukan/n711",
  "カチコール": "https://yakkun.com/za/zukan/n712",
  "クレベース": "https://yakkun.com/za/zukan/n713",
  "クレベース(ヒスイのすがた)": "https://yakkun.com/za/zukan/n713h",
  "オンバット": "https://yakkun.com/za/zukan/n714",
  "オンバーン": "https://yakkun.com/za/zukan/n715",
  "イベルタル": "https://yakkun.com/za/zukan/n717",
  "ジガルデ(１０％フォルム)": "https://yakkun.com/za/zukan/n718t",
  "ジガルデ(５０％フォルム)": "https://yakkun.com/za/zukan/n718",
  "ジガルデ(パーフェクトフォルム)": "https://yakkun.com/za/zukan/n718c",
  "メガジガルデ": "https://yakkun.com/za/zukan/n718m",
  "ディアンシー": "https://yakkun.com/za/zukan/n719",
  "メガディアンシー": "https://yakkun.com/za/zukan/n719m",
  "フーパ(いましめられしフーパ)": "https://yakkun.com/za/zukan/n720",
  "フーパ(ときはなたれしフーパ)": "https://yakkun.com/za/zukan/n720u",
  "ボルケニオン": "https://yakkun.com/za/zukan/n721",
  "モクロー": "https://yakkun.com/sv/zukan/n722",
  "フクスロー": "https://yakkun.com/sv/zukan/n723",
  "ジュナイパー": "https://yakkun.com/sv/zukan/n724",
  "ジュナイパー(ヒスイのすがた)": "https://yakkun.com/sv/zukan/n724h",
  "ニャビー": "https://yakkun.com/sv/zukan/n725",
  "ニャヒート": "https://yakkun.com/sv/zukan/n726",
  "ガオガエン": "https://yakkun.com/sv/zukan/n727",
  "アシマリ": "https://yakkun.com/sv/zukan/n728",
  "オシャマリ": "https://yakkun.com/sv/zukan/n729",
  "アシレーヌ": "https://yakkun.com/sv/zukan/n730",
  "ツツケラ": "https://yakkun.com/sv/zukan/n731",
  "ケララッパ": "https://yakkun.com/sv/zukan/n732",
  "ドデカバシ": "https://yakkun.com/sv/zukan/n733",
  "ヤングース": "https://yakkun.com/sv/zukan/n734",
  "デカグース": "https://yakkun.com/sv/zukan/n735",
  "アゴジムシ": "https://yakkun.com/sv/zukan/n736",
  "デンヂムシ": "https://yakkun.com/sv/zukan/n737",
  "クワガノン": "https://yakkun.com/sv/zukan/n738",
  "マケンカニ": "https://yakkun.com/za/zukan/n739",
  "ケケンカニ": "https://yakkun.com/za/zukan/n740",
  "オドリドリ(ぱちぱちスタイル)": "https://yakkun.com/sv/zukan/n741p",
  "オドリドリ(ふらふらスタイル)": "https://yakkun.com/sv/zukan/n741f",
  "オドリドリ(まいまいスタイル)": "https://yakkun.com/sv/zukan/n741m",
  "オドリドリ(めらめらスタイル)": "https://yakkun.com/sv/zukan/n741",
  "アブリー": "https://yakkun.com/sv/zukan/n742",
  "アブリボン": "https://yakkun.com/sv/zukan/n743",
  "イワンコ": "https://yakkun.com/sv/zukan/n744",
  "ルガルガン(たそがれのすがた)": "https://yakkun.com/sv/zukan/n745d",
  "ルガルガン(まひるのすがた)": "https://yakkun.com/sv/zukan/n745",
  "ルガルガン(まよなかのすがた)": "https://yakkun.com/sv/zukan/n745f",
  "ヨワシ(たんどくのすがた)": "https://yakkun.com/swsh/zukan/n746",
  "ヨワシ(むれたすがた)": "https://yakkun.com/swsh/zukan/n746f",
  "ヒドイデ": "https://yakkun.com/sv/zukan/n747",
  "ドヒドイデ": "https://yakkun.com/sv/zukan/n748",
  "ドロバンコ": "https://yakkun.com/sv/zukan/n749",
  "バンバドロ": "https://yakkun.com/sv/zukan/n750",
  "シズクモ": "https://yakkun.com/sv/zukan/n751",
  "オニシズクモ": "https://yakkun.com/sv/zukan/n752",
  "カリキリ": "https://yakkun.com/sv/zukan/n753",
  "ラランテス": "https://yakkun.com/sv/zukan/n754",
  "ネマシュ": "https://yakkun.com/swsh/zukan/n755",
  "マシェード": "https://yakkun.com/swsh/zukan/n756",
  "ヤトウモリ": "https://yakkun.com/sv/zukan/n757",
  "エンニュート": "https://yakkun.com/sv/zukan/n758",
  "ヌイコグマ": "https://yakkun.com/swsh/zukan/n759",
  "キテルグマ": "https://yakkun.com/swsh/zukan/n760",
  "アマカジ": "https://yakkun.com/sv/zukan/n761",
  "アママイコ": "https://yakkun.com/sv/zukan/n762",
  "アマージョ": "https://yakkun.com/sv/zukan/n763",
  "キュワワー": "https://yakkun.com/sv/zukan/n764",
  "ヤレユータン": "https://yakkun.com/sv/zukan/n765",
  "ナゲツケサル": "https://yakkun.com/sv/zukan/n766",
  "コソクムシ": "https://yakkun.com/za/zukan/n767",
  "グソクムシャ": "https://yakkun.com/za/zukan/n768",
  "スナバァ": "https://yakkun.com/za/zukan/n769",
  "シロデスナ": "https://yakkun.com/za/zukan/n770",
  "ナマコブシ": "https://yakkun.com/swsh/zukan/n771",
  "タイプ：ヌル": "https://yakkun.com/swsh/zukan/n772",
  "ネッコアラ": "https://yakkun.com/sv/zukan/n775",
  "バクガメス": "https://yakkun.com/swsh/zukan/n776",
  "トゲデマル": "https://yakkun.com/swsh/zukan/n777",
  "ハギギシリ": "https://yakkun.com/sv/zukan/n779",
  "ジジーロン": "https://yakkun.com/za/zukan/n780",
  "メガジジーロン": "https://yakkun.com/za/zukan/n780m",
  "ダダリン": "https://yakkun.com/swsh/zukan/n781",
  "ジャラコ": "https://yakkun.com/sv/zukan/n782",
  "ジャランゴ": "https://yakkun.com/sv/zukan/n783",
  "ジャラランガ": "https://yakkun.com/sv/zukan/n784",
  "カプ・コケコ": "https://yakkun.com/swsh/zukan/n785",
  "カプ・テテフ": "https://yakkun.com/swsh/zukan/n786",
  "カプ・ブルル": "https://yakkun.com/swsh/zukan/n787",
  "カプ・レヒレ": "https://yakkun.com/swsh/zukan/n788",
  "コスモッグ": "https://yakkun.com/sv/zukan/n789",
  "コスモウム": "https://yakkun.com/sv/zukan/n790",
  "ソルガレオ": "https://yakkun.com/sv/zukan/n791",
  "ルナアーラ": "https://yakkun.com/sv/zukan/n792",
  "ウツロイド": "https://yakkun.com/swsh/zukan/n793",
  "マッシブーン": "https://yakkun.com/swsh/zukan/n794",
  "フェローチェ": "https://yakkun.com/swsh/zukan/n795",
  "デンジュモク": "https://yakkun.com/swsh/zukan/n796",
  "テッカグヤ": "https://yakkun.com/swsh/zukan/n797",
  "カミツルギ": "https://yakkun.com/swsh/zukan/n798",
  "アクジキング": "https://yakkun.com/swsh/zukan/n799",
  "ネクロズマ": "https://yakkun.com/sv/zukan/n800",
  "ネクロズマ(あかつきのつばさ)": "https://yakkun.com/sv/zukan/n800m",
  "ネクロズマ(ウルトラネクロズマ)": "https://yakkun.com/sm/zukan/n800u",
  "ネクロズマ(たそがれのたてがみ)": "https://yakkun.com/sv/zukan/n800s",
  "マギアナ": "https://yakkun.com/za/zukan/n801",
  "マーシャドー": "https://yakkun.com/za/zukan/n802",
  "ベベノム": "https://yakkun.com/swsh/zukan/n803",
  "アーゴヨン": "https://yakkun.com/swsh/zukan/n804",
  "ツンデツンデ": "https://yakkun.com/swsh/zukan/n805",
  "ズガドーン": "https://yakkun.com/swsh/zukan/n806",
  "ゼラオラ": "https://yakkun.com/za/zukan/n807",
  "メルタン": "https://yakkun.com/za/zukan/n808",
  "メルメタル": "https://yakkun.com/za/zukan/n809",
  "サルノリ": "https://yakkun.com/sv/zukan/n810",
  "バチンキー": "https://yakkun.com/sv/zukan/n811",
  "ゴリランダー": "https://yakkun.com/sv/zukan/n812",
  "ヒバニー": "https://yakkun.com/sv/zukan/n813",
  "ラビフット": "https://yakkun.com/sv/zukan/n814",
  "エースバーン": "https://yakkun.com/sv/zukan/n815",
  "メッソン": "https://yakkun.com/sv/zukan/n816",
  "ジメレオン": "https://yakkun.com/sv/zukan/n817",
  "インテレオン": "https://yakkun.com/sv/zukan/n818",
  "ホシガリス": "https://yakkun.com/sv/zukan/n819",
  "ヨクバリス": "https://yakkun.com/sv/zukan/n820",
  "ココガラ": "https://yakkun.com/za/zukan/n821",
  "アオガラス": "https://yakkun.com/za/zukan/n822",
  "アーマーガア": "https://yakkun.com/za/zukan/n823",
  "サッチムシ": "https://yakkun.com/swsh/zukan/n824",
  "レドームシ": "https://yakkun.com/swsh/zukan/n825",
  "イオルブ": "https://yakkun.com/swsh/zukan/n826",
  "クスネ": "https://yakkun.com/za/zukan/n827",
  "フォクスライ": "https://yakkun.com/za/zukan/n828",
  "ヒメンカ": "https://yakkun.com/swsh/zukan/n829",
  "ワタシラガ": "https://yakkun.com/swsh/zukan/n830",
  "ウールー": "https://yakkun.com/swsh/zukan/n831",
  "バイウールー": "https://yakkun.com/swsh/zukan/n832",
  "カムカメ": "https://yakkun.com/sv/zukan/n833",
  "カジリガメ": "https://yakkun.com/sv/zukan/n834",
  "ワンパチ": "https://yakkun.com/swsh/zukan/n835",
  "パルスワン": "https://yakkun.com/swsh/zukan/n836",
  "タンドン": "https://yakkun.com/sv/zukan/n837",
  "トロッゴン": "https://yakkun.com/sv/zukan/n838",
  "セキタンザン": "https://yakkun.com/sv/zukan/n839",
  "カジッチュ": "https://yakkun.com/sv/zukan/n840",
  "アップリュー": "https://yakkun.com/sv/zukan/n841",
  "タルップル": "https://yakkun.com/sv/zukan/n842",
  "スナヘビ": "https://yakkun.com/sv/zukan/n843",
  "サダイジャ": "https://yakkun.com/sv/zukan/n844",
  "ウッウ": "https://yakkun.com/sv/zukan/n845",
  "サシカマス": "https://yakkun.com/sv/zukan/n846",
  "カマスジョー": "https://yakkun.com/sv/zukan/n847",
  "エレズン": "https://yakkun.com/za/zukan/n848",
  "ストリンダー(ハイなすがた)": "https://yakkun.com/za/zukan/n849",
  "ストリンダー(ローなすがた)": "https://yakkun.com/za/zukan/n849f",
  "ヤクデ": "https://yakkun.com/swsh/zukan/n850",
  "マルヤクデ": "https://yakkun.com/swsh/zukan/n851",
  "タタッコ": "https://yakkun.com/za/zukan/n852",
  "オトスパス": "https://yakkun.com/za/zukan/n853",
  "ミブリム": "https://yakkun.com/sv/zukan/n856",
  "テブリム": "https://yakkun.com/sv/zukan/n857",
  "ブリムオン": "https://yakkun.com/sv/zukan/n858",
  "ベロバー": "https://yakkun.com/sv/zukan/n859",
  "ギモー": "https://yakkun.com/sv/zukan/n860",
  "オーロンゲ": "https://yakkun.com/sv/zukan/n861",
  "タチフサグマ": "https://yakkun.com/swsh/zukan/n862",
  "ニャイキング": "https://yakkun.com/za/zukan/n863",
  "サニゴーン": "https://yakkun.com/swsh/zukan/n864",
  "ネギガナイト": "https://yakkun.com/za/zukan/n865",
  "バリコオル": "https://yakkun.com/za/zukan/n866",
  "デスバーン": "https://yakkun.com/za/zukan/n867",
  "マホミル": "https://yakkun.com/sv/zukan/n868",
  "タイレーツ": "https://yakkun.com/za/zukan/n870",
  "メガタイレーツ": "https://yakkun.com/za/zukan/n870m",
  "バチンウニ": "https://yakkun.com/sv/zukan/n871",
  "ユキハミ": "https://yakkun.com/sv/zukan/n872",
  "モスノウ": "https://yakkun.com/sv/zukan/n873",
  "イシヘンジン": "https://yakkun.com/sv/zukan/n874",
  "コオリッポ(アイスフェイス)": "https://yakkun.com/sv/zukan/n875",
  "コオリッポ(ナイスフェイス)": "https://yakkun.com/sv/zukan/n875f",
  "イエッサン(オスのすがた)": "https://yakkun.com/za/zukan/n876",
  "イエッサン(メスのすがた)": "https://yakkun.com/za/zukan/n876f",
  "ゾウドウ": "https://yakkun.com/sv/zukan/n878",
  "ダイオウドウ": "https://yakkun.com/sv/zukan/n879",
  "パッチラゴン": "https://yakkun.com/swsh/zukan/n880",
  "パッチルドン": "https://yakkun.com/swsh/zukan/n881",
  "ウオノラゴン": "https://yakkun.com/swsh/zukan/n882",
  "ウオチルドン": "https://yakkun.com/swsh/zukan/n883",
  "ジュラルドン": "https://yakkun.com/sv/zukan/n884",
  "ドラメシヤ": "https://yakkun.com/sv/zukan/n885",
  "ドロンチ": "https://yakkun.com/sv/zukan/n886",
  "ドラパルト": "https://yakkun.com/sv/zukan/n887",
  "ザシアン(けんのおう)": "https://yakkun.com/sv/zukan/n888f",
  "ザシアン(れきせんのゆうしゃ)": "https://yakkun.com/sv/zukan/n888",
  "ザマゼンタ(たてのおう)": "https://yakkun.com/sv/zukan/n889f",
  "ザマゼンタ(れきせんのゆうしゃ)": "https://yakkun.com/sv/zukan/n889",
  "ムゲンダイナ": "https://yakkun.com/sv/zukan/n890",
  "ダクマ": "https://yakkun.com/sv/zukan/n891",
  "ウーラオス(いちげきのかた)": "https://yakkun.com/sv/zukan/n892",
  "ウーラオス(れんげきのかた)": "https://yakkun.com/sv/zukan/n892r",
  "ザルード": "https://yakkun.com/sv/zukan/n893",
  "レジエレキ": "https://yakkun.com/sv/zukan/n894",
  "レジドラゴ": "https://yakkun.com/sv/zukan/n895",
  "ブリザポス": "https://yakkun.com/sv/zukan/n896",
  "レイスポス": "https://yakkun.com/sv/zukan/n897",
  "バドレックス": "https://yakkun.com/sv/zukan/n898",
  "バドレックス(こくばじょうのすがた)": "https://yakkun.com/sv/zukan/n898b",
  "バドレックス(はくばじょうのすがた)": "https://yakkun.com/sv/zukan/n898w",
  "アヤシシ": "https://yakkun.com/sv/zukan/n899",
  "バサギリ": "https://yakkun.com/za/zukan/n900",
  "ガチグマ": "https://yakkun.com/sv/zukan/n901",
  "ガチグマ(アカツキ)": "https://yakkun.com/sv/zukan/n901f",
  "イダイトウ(オスのすがた)": "https://yakkun.com/sv/zukan/n902",
  "イダイトウ(メスのすがた)": "https://yakkun.com/sv/zukan/n902f",
  "オオニューラ": "https://yakkun.com/sv/zukan/n903",
  "ハリーマン": "https://yakkun.com/za/zukan/n904",
  "ラブトロス(けしんフォルム)": "https://yakkun.com/sv/zukan/n905",
  "ラブトロス(れいじゅうフォルム)": "https://yakkun.com/sv/zukan/n905a",
  "ニャオハ": "https://yakkun.com/sv/zukan/n906",
  "ニャローテ": "https://yakkun.com/sv/zukan/n907",
  "マスカーニャ": "https://yakkun.com/sv/zukan/n908",
  "ホゲータ": "https://yakkun.com/sv/zukan/n909",
  "アチゲータ": "https://yakkun.com/sv/zukan/n910",
  "ラウドボーン": "https://yakkun.com/sv/zukan/n911",
  "クワッス": "https://yakkun.com/sv/zukan/n912",
  "ウェルカモ": "https://yakkun.com/sv/zukan/n913",
  "ウェーニバル": "https://yakkun.com/sv/zukan/n914",
  "グルトン": "https://yakkun.com/sv/zukan/n915",
  "パフュートン(オスのすがた)": "https://yakkun.com/sv/zukan/n916",
  "パフュートン(メスのすがた)": "https://yakkun.com/sv/zukan/n916f",
  "タマンチュラ": "https://yakkun.com/sv/zukan/n918",
  "ワナイダー": "https://yakkun.com/sv/zukan/n919",
  "マメバッタ": "https://yakkun.com/sv/zukan/n920",
  "エクスレッグ": "https://yakkun.com/sv/zukan/n921",
  "パモ": "https://yakkun.com/sv/zukan/n954",
  "パモット": "https://yakkun.com/sv/zukan/n955",
  "パーモット": "https://yakkun.com/sv/zukan/n956",
  "ワッカネズミ": "https://yakkun.com/sv/zukan/n945",
  "パピモッチ": "https://yakkun.com/za/zukan/n970",
  "バウッツェル": "https://yakkun.com/za/zukan/n971",
  "ミニーブ": "https://yakkun.com/sv/zukan/n935",
  "オリーニョ": "https://yakkun.com/sv/zukan/n936",
  "オリーヴァ": "https://yakkun.com/sv/zukan/n937",
  "コジオ": "https://yakkun.com/za/zukan/n963",
  "ジオヅム": "https://yakkun.com/za/zukan/n964",
  "キョジオーン": "https://yakkun.com/za/zukan/n965",
  "カルボウ": "https://yakkun.com/za/zukan/n1003",
  "グレンアルマ": "https://yakkun.com/za/zukan/n1004",
  "ソウブレイズ": "https://yakkun.com/za/zukan/n1005",
  "ズピカ": "https://yakkun.com/sv/zukan/n940",
  "ハラバリー": "https://yakkun.com/sv/zukan/n941",
  "カイデン": "https://yakkun.com/sv/zukan/n957",
  "タイカイデン": "https://yakkun.com/sv/zukan/n958",
  "オラチフ": "https://yakkun.com/za/zukan/n972",
  "マフィティフ": "https://yakkun.com/za/zukan/n973",
  "シルシュルー": "https://yakkun.com/za/zukan/n968",
  "タギングル": "https://yakkun.com/za/zukan/n969",
  "アノクサ": "https://yakkun.com/sv/zukan/n974",
  "アノホラグサ": "https://yakkun.com/sv/zukan/n975",
  "ノノクラゲ": "https://yakkun.com/sv/zukan/n1006",
  "リククラゲ": "https://yakkun.com/sv/zukan/n1007",
  "ガケガニ": "https://yakkun.com/sv/zukan/n962",
  "カプサイジ": "https://yakkun.com/za/zukan/n938",
  "スコヴィラン": "https://yakkun.com/za/zukan/n939",
  "シガロコ": "https://yakkun.com/sv/zukan/n922",
  "ベラカス": "https://yakkun.com/sv/zukan/n923",
  "ヒラヒナ": "https://yakkun.com/sv/zukan/n926",
  "クエスパトラ": "https://yakkun.com/sv/zukan/n927",
  "カヌチャン": "https://yakkun.com/za/zukan/n1000",
  "ナカヌチャン": "https://yakkun.com/za/zukan/n1001",
  "デカヌチャン": "https://yakkun.com/za/zukan/n1002",
  "ウミディグダ": "https://yakkun.com/sv/zukan/n929",
  "ウミトリオ": "https://yakkun.com/sv/zukan/n930",
  "オトシドリ": "https://yakkun.com/sv/zukan/n959",
  "ナミイルカ": "https://yakkun.com/sv/zukan/n933",
  "イルカマン(ナイーブフォルム)": "https://yakkun.com/sv/zukan/n934",
  "イルカマン(マイティフォルム)": "https://yakkun.com/sv/zukan/n934f",
  "ブロロン": "https://yakkun.com/sv/zukan/n942",
  "ブロロローム": "https://yakkun.com/sv/zukan/n943",
  "モトトカゲ": "https://yakkun.com/za/zukan/n953",
  "ミミズズ": "https://yakkun.com/sv/zukan/n944",
  "キラーメ": "https://yakkun.com/za/zukan/n966",
  "キラフロル": "https://yakkun.com/za/zukan/n967",
  "ボチ": "https://yakkun.com/za/zukan/n924",
  "ハカドッグ": "https://yakkun.com/za/zukan/n925",
  "カラミンゴ": "https://yakkun.com/za/zukan/n961",
  "アルクジラ": "https://yakkun.com/sv/zukan/n947",
  "ハルクジラ": "https://yakkun.com/sv/zukan/n948",
  "ミガルーサ": "https://yakkun.com/sv/zukan/n932",
  "ヘイラッシャ": "https://yakkun.com/za/zukan/n931",
  "コノヨザル": "https://yakkun.com/za/zukan/n1010",
  "ドオー": "https://yakkun.com/sv/zukan/n1009",
  "リキキリン": "https://yakkun.com/sv/zukan/n928",
  "ドドゲザン": "https://yakkun.com/sv/zukan/n1008",
  "イダイナキバ": "https://yakkun.com/sv/zukan/n978",
  "サケブシッポ": "https://yakkun.com/sv/zukan/n982",
  "アラブルタケ": "https://yakkun.com/sv/zukan/n979",
  "ハバタクカミ": "https://yakkun.com/sv/zukan/n983",
  "チヲハウハネ": "https://yakkun.com/sv/zukan/n984",
  "スナノケガワ": "https://yakkun.com/sv/zukan/n981",
  "テツノワダチ": "https://yakkun.com/sv/zukan/n986",
  "テツノツツミ": "https://yakkun.com/sv/zukan/n992",
  "テツノカイナ": "https://yakkun.com/sv/zukan/n989",
  "テツノコウベ": "https://yakkun.com/sv/zukan/n990",
  "テツノドクガ": "https://yakkun.com/sv/zukan/n988",
  "テツノイバラ": "https://yakkun.com/sv/zukan/n991",
  "セビエ": "https://yakkun.com/za/zukan/n949",
  "セゴール": "https://yakkun.com/za/zukan/n950",
  "セグレイブ": "https://yakkun.com/za/zukan/n951",
  "コレクレー(とほフォルム)": "https://yakkun.com/za/zukan/n976f",
  "コレクレー(はこフォルム)": "https://yakkun.com/za/zukan/n976",
  "サーフゴー": "https://yakkun.com/za/zukan/n977",
  "チオンジェン": "https://yakkun.com/sv/zukan/n996",
  "パオジアン": "https://yakkun.com/sv/zukan/n995",
  "ディンルー": "https://yakkun.com/sv/zukan/n994",
  "イーユイ": "https://yakkun.com/sv/zukan/n997",
  "トドロクツキ": "https://yakkun.com/sv/zukan/n985",
  "テツノブジン": "https://yakkun.com/sv/zukan/n993",
  "コライドン(かんぜんけいたい)": "https://yakkun.com/sv/zukan/n998",
  "ミライドン(コンプリートモード)": "https://yakkun.com/sv/zukan/n999",
  "ウネルミナモ": "https://yakkun.com/sv/zukan/n980",
  "テツノイサハ": "https://yakkun.com/sv/zukan/n987",
  "カミッチュ": "https://yakkun.com/sv/zukan/n1012",
  "イイネイヌ": "https://yakkun.com/sv/zukan/n1014",
  "マシマシラ": "https://yakkun.com/sv/zukan/n1015",
  "キチキギス": "https://yakkun.com/sv/zukan/n1016",
  "オーガポン(いしずえのめん)": "https://yakkun.com/sv/zukan/n1011c",
  "オーガポン(いどのめん)": "https://yakkun.com/sv/zukan/n1011w",
  "オーガポン(かまどのめん)": "https://yakkun.com/sv/zukan/n1011h",
  "オーガポン(みどりのめん)": "https://yakkun.com/sv/zukan/n1011",
  "ブリジュラス": "https://yakkun.com/sv/zukan/n1023",
  "カミツオロチ": "https://yakkun.com/sv/zukan/n1013",
  "ウガツホムラ": "https://yakkun.com/sv/zukan/n1017",
  "タケルライコ": "https://yakkun.com/sv/zukan/n1018",
  "テツノイワオ": "https://yakkun.com/sv/zukan/n1020",
  "テツノカシラ": "https://yakkun.com/sv/zukan/n1019",
  "テラパゴス(ステラフォルム)": "https://yakkun.com/sv/zukan/n1021s",
  "テラパゴス(テラスタルフォルム)": "https://yakkun.com/sv/zukan/n1021t",
  "テラパゴス(ノーマルフォルム)": "https://yakkun.com/sv/zukan/n1021",
  "モモワロウ": "https://yakkun.com/sv/zukan/n1022"
}
